pyparous/__init__.py
pyparous/main.py
pyparous-0.4.dist-info/LICENSE
pyparous-0.4.dist-info/METADATA
pyparous-0.4.dist-info/WHEEL
pyparous-0.4.dist-info/top_level.txt
pyparous-0.4.dist-info/RECORD
