Metadata-Version: 2.1
Name: pyparous
Version: 0.4
License-File: LICENSE
